traderstreamer.py
node_1/__init__.py
node_1/memory.py
node_1/node.py
node_1/services/__init__.py
node_1/services/account_streamer_svc.py
node_1/services/bar_streamer_svc.py
node_1/services/data_handler_svc.py
node_1/services/data_server_svc.py
node_1/services/market_streamer_svc.py
node_1/services/second_bar_svc.py
node_2/__init__.py
node_2/memory.py
node_2/node.py
node_2/services/__init__.py
node_2/services/account_streamer_svc.py
node_2/services/bar_streamer_svc.py
node_2/services/data_handler_svc.py
node_2/services/data_server_svc.py
node_2/services/market_streamer_svc.py
node_2/services/second_bar_svc.py
node_3/__init__.py
node_3/memory.py
node_3/node.py
node_3/services/__init__.py
node_3/services/market_streamer_svc.py
node_3/services/second_bar_svc.py
periphery/__init__.py
periphery/hour_bar_deque.py
periphery/local_stream.py
periphery/proxy_data_handler.py
scripts/__init__.py
scripts/data_handler.py
scripts/data_merger.py
scripts/even_node.py
scripts/odd_node.py
scripts/services.py
scripts/svc_node.py
scripts/test_node.py
utils/__init__.py
utils/docker_handler.py
utils/telegram_logger.py
traderstreamer-0.0.11.dist-info/METADATA
traderstreamer-0.0.11.dist-info/WHEEL
traderstreamer-0.0.11.dist-info/top_level.txt
traderstreamer-0.0.11.dist-info/RECORD
