Metadata-Version: 2.1
Name: traderstreamer
Version: 0.0.11
Summary: Coin Trader Streamers
Home-page: UNKNOWN
Author: Phillip Park
Author-email: ppark9553@gmail.com
License: UNKNOWN
Platform: UNKNOWN
Requires-Dist: python-dotenv
Requires-Dist: tradernetwork
Requires-Dist: cointraderkr
